[
    {
        "id": "1",
        "name": "Classic Spaghetti Carbonara",
        "description": "A delicious Italian pasta dish with creamy egg and cheese sauce.",
        "ingredients": [
            "Spaghetti",
            "Pork",
            "Peanuts or Nuts",
            "Bacon",
            "Eggs",
            "Parmesan Cheese",
            "Ground Black Pepper"
        ],
        "steps": [
            "Cook the spaghetti in boiling salted water until al dente.",
            "In a separate pan, fry the bacon until crispy. Remove from heat and drain excess fat.",
            "In a bowl, whisk together eggs and grated Parmesan cheese.",
            "Once the spaghetti is cooked, drain it and immediately toss it with the egg mixture.",
            "The heat from the pasta will cook the eggs and create a creamy sauce.",
            "Add the crispy bacon and black pepper to the pasta. Toss everything together.",
            "Serve hot, garnished with additional Parmesan cheese a nd black pepper if desired."
        ],
        "main_ingredient": "pork",
        "prep_time": "10 minutes",
        "cook_time": "15 minutes",
        "total_time": "25 minutes",
        "servings": "4",
        "image_url": "http://localhost:5050/images/recipe_01.jpg"
    },
    {
        "id": "2",
        "name": "Chicken Alfredo Pasta",
        "description": "Creamy pasta dish with tender chicken and Parmesan cheese sauce.",
        "ingredients": [
            "Chicken",
            "Chicken Breasts",
            "Fettuccine",
            "Heavy Cream",
            "Butter",
            "Garlic",
            "Parmesan Cheese"
        ],
        "main_ingredient": "chicken",
        "steps": [
            "Cook the fettuccine as directed; drain and set aside.",
            "Saute chicken in butter until cooked; add minced garlic.",
            "Pour in heavy cream and simmer until thickened.",
            "Stir in grated Parmesan cheese until melted.",
            "Combine sauce with pasta and serve hot."
        ],
        "prep_time": "15 minutes",
        "cook_time": "20 minutes",
        "total_time": "35 minutes",
        "servings": "4",
        "image_url": "http://localhost:5050/images/recipe_02.jpg"
    },
    {
        "id": "3",
        "name": "Grilled Steak with Garlic Butter",
        "description": "Juicy grilled steak with flavorful garlic butter.",
        "ingredients": ["Ribeye Steak", "Beef", "Garlic", "Butter", "Rosemary", "Salt", "Pepper"],
        "main_ingredient": "beef",
        "steps": [
            "Season the steak with salt, pepper, and chopped rosemary.",
            "Grill the steak to your desired doneness.",
            "In a pan, melt butter and saute minced garlic until fragrant.",
            "Pour the garlic butter over the grilled steak and serve."
        ],
        "prep_time": "10 minutes",
        "cook_time": "15 minutes",
        "total_time": "25 minutes",
        "servings": "2",
        "image_url": "http://localhost:5050/images/recipe_03.jpg"
    },
    {
        "id": "4",
        "name": "Baked Lemon Herb Salmon",
        "description": "Healthy and flavorful salmon baked with lemon and herbs.",
        "ingredients": [
            "Salmon Fillets",
            "Peanuts or Nuts",
            "Fish",
            "Lemon",
            "Olive Oil",
            "Garlic",
            "Thyme",
            "Salt",
            "Pepper"
        ],
        "main_ingredient": "fish",
        "steps": [
            "Preheat the oven to 375°F (190°C).",
            "Place the salmon fillets on a baking sheet.",
            "Drizzle with olive oil and squeeze lemon juice over the salmon.",
            "Sprinkle with minced garlic, chopped thyme, salt, and pepper.",
            "Bake in the preheated oven for about 15-20 minutes, or until the salmon is cooked through.",
            "Serve hot, garnished with additional lemon slices and fresh thyme if desired."
        ],
        "prep_time": "10 minutes",
        "cook_time": "20 minutes",
        "total_time": "30 minutes",
        "servings": "2",
        "image_url": "http://localhost:5050/images/recipe_04.jpg"
    },
    {
        "id": "5",
        "name": "Margherita Pizza",
        "description": "Classic Italian pizza with tomato sauce, fresh mozzarella, and basil.",
        "ingredients": ["Pizza Dough", "Vegi", "Tomato Sauce", "Fresh Mozzarella", "Fresh Basil Leaves", "Olive Oil"],
        "main_ingredient": "vegi",
        "steps": [
            "Preheat the oven to the highest temperature (usually 500°F/260°C).",
            "Roll out the pizza dough on a floured surface to your desired thickness.",
            "Transfer the rolled-out dough to a baking sheet or pizza stone.",
            "Spread a thin layer of tomato sauce over the dough.",
            "Arrange slices of fresh mozzarella on top of the sauce.",
            "Bake in the preheated oven for about 10-12 minutes, or until the crust is golden and the cheese is bubbly and slightly browned.",
            "Remove from the oven and top with fresh basil leaves.",
            "Drizzle with olive oil and serve hot."
        ],
        "prep_time": "20 minutes",
        "cook_time": "12 minutes",
        "total_time": "32 minutes",
        "servings": "4",
        "image_url": "http://localhost:5050/images/recipe_05.jpg"
    },
    {
        "id": "6",
        "name": "Chicken Tikka Masala",
        "description": "A popular Indian curry dish with tender chicken in a rich tomato-based sauce.",
        "ingredients": [
            "Chicken Thighs",
            "Chicken",
            "Yogurt",
            "Tomato Sauce",
            "Garam Masala",
            "Ginger",
            "Garlic",
            "Cream",
            "Shrimp"
        ],
        "main_ingredient": "chicken",
        "steps": [
            "In a bowl, marinate chicken thighs in yogurt, garam masala, ginger, and garlic for at least 30 minutes.",
            "In a pan, cook the marinated chicken until browned and cooked through.",
            "Add tomato sauce and simmer until the sauce thickens.",
            "Stir in the cream to make the sauce rich and creamy.",
            "Serve hot, garnished with chopped cilantro, with steamed rice or naan."
        ],
        "prep_time": "40 minutes",
        "cook_time": "25 minutes",
        "total_time": "1 hour 5 minutes",
        "servings": "4",
        "image_url": "http://localhost:5050/images/recipe_06.jpg"
    },
    {
        "id": "7",
        "name": "Vegetarian Sushi Rolls",
        "description": "Delicious sushi rolls filled with fresh vegetables and served with soy sauce and wasabi.",
        "ingredients": [
            "Sushi Rice",
            "Vegi",
            "Peanuts or Nuts",
            "Nori Sheets",
            "Cucumber",
            "Avocado",
            "Carrot",
            "Soy Sauce",
            "Wasabi"
        ],
        "main_ingredient": "vegi",
        "steps": [
            "Cook the sushi rice as per package instructions and let it cool.",
            "Place a bamboo sushi mat on a clean surface and cover it with plastic wrap.",
            "Place a nori sheet on the mat, shiny side down.",
            "Spread a thin layer of sushi rice on the nori sheet, leaving about 1 inch of space at the top.",
            "Add strips of cucumber, avocado, and carrot along the center of the rice.",
            "Roll the sushi tightly using the bamboo mat, moisten the top edge of the nori with water to seal the roll.",
            "Slice the sushi roll into bite-sized pieces.",
            "Serve with soy sauce and wasabi."
        ],
        "prep_time": "30 minutes",
        "cook_time": "0 minutes",
        "total_time": "30 minutes",
        "servings": "4",
        "image_url": "http://localhost:5050/images/recipe_07.jpg"
    },
    {
        "id": "8",
        "name": "Beef and Broccoli Stir-Fry",
        "description": "Quick and flavorful beef stir-fry with broccoli in a savory sauce.",
        "ingredients": [
            "Beef Strips",
            "Beef",
            "vegi",
            "Broccoli",
            "Soy Sauce",
            "Oyster Sauce",
            "Ginger",
            "Garlic",
            "Sesame Oil"
        ],
        "main_ingredient": "beef",
        "steps": [
            "In a bowl, marinate the beef strips in soy sauce and ginger for 15-20 minutes.",
            "In a wok or large skillet, heat sesame oil and stir-fry the marinated beef until browned. Remove from the wok and set aside.",
            "Stir-fry broccoli in the same wok until crisp-tender.",
            "Add minced garlic and oyster sauce to the broccoli and stir-fry for another minute.",
            "Return the beef to the wok and toss everything together.",
            "Serve hot over steamed rice."
        ],
        "prep_time": "25 minutes",
        "cook_time": "15 minutes",
        "total_time": "40 minutes",
        "servings": "4",
        "image_url": "http://localhost:5050/images/recipe_08.jpg"
    },
    {
        "id": "9",
        "name": "Creamy Tomato Basil Soup",
        "description": "A comforting and creamy tomato soup with fresh basil.",
        "ingredients": ["Tomatoes", "Vegi", "Onion", "Garlic", "Vegetable Broth", "Cream", "Fresh Basil Leaves"],
        "main_ingredient": "vegi",
        "steps": [
            "In a large pot, saute chopped onions and garlic until soft.",
            "Add chopped tomatoes and cook until they break down.",
            "Pour in vegetable broth and bring to a boil. Simmer for 15 minutes.",
            "Use an immersion blender to puree the soup until smooth.",
            "Stir in the cream and chopped fresh basil.",
            "Simmer for an additional 5 minutes.",
            "Season with salt and pepper to taste.",
            "Serve hot, garnished with extra basil leaves and a drizzle of cream if desired."
        ],
        "prep_time": "15 minutes",
        "cook_time": "25 minutes",
        "total_time": "40 minutes",
        "servings": "6",
        "image_url": "http://localhost:5050/images/recipe_09.jpg"
    },
    {
        "id": "10",
        "name": "Shrimp Scampi",
        "description": "Quick and delicious shrimp sauteed in garlic, butter, and white wine sauce.",
        "ingredients": ["Shrimp", "Butter", "Garlic", "White Wine", "Lemon Juice", "Parsley", "Spaghetti"],
        "main_ingredient": "shrimp",
        "steps": [
            "Cook the spaghetti as per package instructions and set aside.",
            "In a large skillet, melt butter and saute minced garlic until fragrant.",
            "Add the shrimp to the skillet and cook until pink and opaque.",
            "Pour in white wine and lemon juice, and let it simmer for a few minutes.",
            "Stir in chopped parsley and season with salt and pepper.",
            "Toss the cooked spaghetti with the shrimp and sauce.",
            "Serve hot, garnished with additional parsley and lemon wedges if desired."
        ],
        "prep_time": "10 minutes",
        "cook_time": "10 minutes",
        "total_time": "20 minutes",
        "servings": "4",
        "image_url": "http://localhost:5050/images/recipe_10.jpg"
    },
    {
        "id": "11",
        "name": "Chicken Parmesan",
        "description": "Breaded chicken topped with marinara sauce and melted mozzarella and Parmesan cheese.",
        "ingredients": [
            "Chicken Breasts",
            "Chicken",
            "Breadcrumbs",
            "Marinara Sauce",
            "Mozzarella Cheese",
            "Parmesan Cheese"
        ],
        "main_ingredient": "chicken",
        "steps": [
            "Preheat the oven to 375°F (190°C).",
            "Season the chicken breasts with salt and pepper.",
            "Dredge the chicken in breadcrumbs until fully coated.",
            "In a pan, heat oil over medium heat and cook the chicken until golden and cooked through.",
            "Place the cooked chicken in a baking dish, top with marinara sauce, mozzarella, and Parmesan cheese.",
            "Bake in the preheated oven for about 15 minutes, or until the cheese is melted and bubbly.",
            "Serve hot, garnished with chopped fresh basil if desired."
        ],
        "prep_time": "15 minutes",
        "cook_time": "20 minutes",
        "total_time": "35 minutes",
        "servings": "4",
        "image_url": "http://localhost:5050/images/recipe_11.jpg"
    },
    {
        "id": "12",
        "name": "Veggie Quinoa Bowl",
        "description": "Healthy and nutritious quinoa bowl with mixed vegetables and chickpeas.",
        "ingredients": [
            "Quinoa",
            "Vegi",
            "Mixed Vegetables (e.g., Bell Peppers, Zucchini, Carrots)",
            "Chickpeas",
            "Feta Cheese",
            "Lemon Dressing"
        ],
        "main_ingredient": "vegi",
        "steps": [
            "Rinse the quinoa thoroughly and cook according to package instructions.",
            "In a pan, saute mixed vegetables and chickpeas until tender.",
            "Toss cooked quinoa with the sauteed vegetables and chickpeas.",
            "Crumble feta cheese over the quinoa bowl.",
            "Drizzle with lemon dressing and toss everything together.",
            "Serve warm or chilled."
        ],
        "prep_time": "10 minutes",
        "cook_time": "20 minutes",
        "total_time": "30 minutes",
        "servings": "4",
        "image_url": "http://localhost:5050/images/recipe_12.jpg"
    },
    {
        "id": "13",
        "name": "Thai Red Curry with Tofu",
        "description": "A flavorful Thai curry with tofu, vegetables, and aromatic spices.",
        "ingredients": ["Tofu", "Vegi", "Red Curry Paste", "Coconut Milk", "Bell Peppers", "Bamboo Shoots"],
        "main_ingredient": "vegi",
        "steps": [
            "In a wok or large skillet, saute tofu until lightly browned. Set aside.",
            "In the same wok, add red curry paste and cook until fragrant.",
            "Pour in coconut milk and bring to a simmer.",
            "Add sliced bell peppers and bamboo shoots to the curry sauce.",
            "Simmer until the vegetables are cooked and the sauce thickens.",
            "Return the sauteed tofu to the wok and mix everything together.",
            "Serve hot, garnished with fresh cilantro, with steamed rice."
        ],
        "prep_time": "20 minutes",
        "cook_time": "15 minutes",
        "total_time": "35 minutes",
        "servings": "4",
        "image_url": "http://localhost:5050/images/recipe_13.jpg"
    },
    {
        "id": "14",
        "name": "Baked Ziti",
        "description": "Baked pasta dish with ziti, marinara sauce, and melted cheese.",
        "ingredients": [
            "Ziti Pasta",
            "Vegi",
            "Marinara Sauce",
            "Ricotta Cheese",
            "Mozzarella Cheese",
            "Parmesan Cheese"
        ],
        "main_ingredient": "vegi",
        "steps": [
            "Preheat the oven to 375°F (190°C).",
            "Cook the ziti pasta according to package instructions.",
            "In a baking dish, layer cooked ziti, marinara sauce, ricotta cheese, and mozzarella.",
            "Repeat the layers until all ingredients are used, finishing with mozzarella on top.",
            "Sprinkle grated Parmesan cheese over the top layer.",
            "Bake in the preheated oven for about 20-25 minutes, or until the cheese is melted and bubbly.",
            "Serve hot, garnished with chopped fresh basil if desired."
        ],
        "prep_time": "15 minutes",
        "cook_time": "25 minutes",
        "total_time": "40 minutes",
        "servings": "6",
        "image_url": "http://localhost:5050/images/recipe_14.jpg"
    },
    {
        "id": "15",
        "name": "Greek Salad",
        "description": "Refreshing salad with cucumbers, tomatoes, olives, and feta cheese.",
        "ingredients": [
            "Cucumbers",
            "Tomatoes",
            "Red Onions",
            "Kalamata Olives",
            "Feta Cheese",
            "Oregano",
            "Olive Oil",
            "Vegi"
        ],
        "main_ingredient": "vegi",
        "steps": [
            "Slice cucumbers, tomatoes, and red onions and place them in a large salad bowl.",
            "Add Kalamata olives and crumbled feta cheese to the bowl.",
            "Drizzle olive oil over the salad.",
            "Sprinkle dried oregano on top.",
            "Toss everything together until well combined.",
            "Serve chilled as a side dish or with crusty bread for a light meal."
        ],
        "prep_time": "15 minutes",
        "cook_time": "0 minutes",
        "total_time": "15 minutes",
        "servings": "4",
        "image_url": "http://localhost:5050/images/recipe_15.jpg"
    },
    {
        "id": "16",
        "name": "Caramelized Onion and Mushroom Tart",
        "description": "Savory tart with caramelized onions, mushrooms, and cheese.",
        "ingredients": ["Puff Pastry", "Vegi", "Onions", "Mushrooms", "Balsamic Vinegar", "Thyme", "Gruyere Cheese"],
        "main_ingredient": "vegi",
        "steps": [
            "Preheat the oven to 400°F (200°C).",
            "Roll out the puff pastry on a floured surface to fit a baking sheet.",
            "In a pan, saute sliced onions until caramelized.",
            "Add sliced mushrooms and cook until tender.",
            "Stir in balsamic vinegar and fresh thyme.",
            "Spread the caramelized onion and mushroom mixture over the puff pastry.",
            "Top with shredded Gruyere cheese.",
            "Bake in the preheated oven for about 20-25 minutes, or until the pastry is golden and the cheese is melted.",
            "Serve hot or at room temperature."
        ],
        "prep_time": "15 minutes",
        "cook_time": "30 minutes",
        "total_time": "45 minutes",
        "servings": "6",
        "image_url": "http://localhost:5050/images/recipe_16.jpg"
    },
    {
        "id": "17",
        "name": "Chicken Caesar Salad",
        "description": "Classic Caesar salad with grilled chicken and homemade dressing.",
        "ingredients": [
            "Chicken Breasts",
            "Chicken",
            "Romaine Lettuce",
            "Croutons",
            "Parmesan Cheese",
            "Caesar Dressing"
        ],
        "main_ingredient": "chicken",
        "steps": [
            "Season the chicken breasts with salt and pepper.",
            "Grill the chicken until cooked through and slice it into strips.",
            "Wash and dry the romaine lettuce, then tear it into bite-sized pieces.",
            "In a large bowl, toss the romaine with Caesar dressing until well coated.",
            "Top the salad with sliced chicken, croutons, and shaved Parmesan cheese.",
            "Serve chilled, garnished with additional Parmesan and cracked black pepper if desired."
        ],
        "prep_time": "15 minutes",
        "cook_time": "15 minutes",
        "total_time": "30 minutes",
        "servings": "4",
        "image_url": "http://localhost:5050/images/recipe_17.jpg"
    },
    {
        "id": "18",
        "name": "Mushroom Risotto",
        "description": "Creamy and flavorful risotto with mushrooms and Parmesan cheese.",
        "ingredients": [
            "Arborio Rice",
            "Mushrooms",
            "Vegetable Broth",
            "White Wine",
            "Onion",
            "Garlic",
            "Parmesan Cheese",
            "Vegi"
        ],
        "main_ingredient": "vegi",
        "steps": [
            "In a saucepan, bring vegetable broth to a simmer and keep it warm.",
            "In a separate large pan, saute chopped onion and minced garlic until translucent.",
            "Add sliced mushrooms and cook until tender.",
            "Add Arborio rice to the pan and cook for a few minutes until lightly toasted.",
            "Pour in white wine and cook until it's mostly absorbed.",
            "Add a ladle of warm vegetable broth to the rice and stir continuously until it's mostly absorbed.",
            "Repeat the process, adding broth one ladle at a time and stirring until the rice is creamy and cooked al dente.",
            "Stir in grated Parmesan cheese until melted and creamy.",
            "Serve hot, garnished with chopped fresh parsley if desired."
        ],
        "prep_time": "10 minutes",
        "cook_time": "30 minutes",
        "total_time": "40 minutes",
        "servings": "4",
        "image_url": "http://localhost:5050/images/recipe_18.jpg"
    },
    {
        "id": "19",
        "name": "Taco Salad",
        "description": "A hearty and satisfying salad with seasoned ground beef and all the taco fixings.",
        "ingredients": [
            "Beef",
            "Ground Beef",
            "Taco Seasoning",
            "Lettuce",
            "Tomatoes",
            "Avocado",
            "Corn",
            "Black Beans",
            "Cheddar Cheese",
            "Tortilla Chips",
            "Salsa",
            "Sour Cream"
        ],
        "main_ingredient": "beef",
        "steps": [
            "In a skillet, cook the ground beef with taco seasoning until browned and fully cooked.",
            "Chop lettuce and tomatoes and place them in a large salad bowl.",
            "Add sliced avocado, corn, and black beans to the salad.",
            "Top with seasoned ground beef and shredded cheddar cheese.",
            "Crush tortilla chips over the salad.",
            "Serve the taco salad with salsa and sour cream on the side.",
            "Toss everything together just before eating."
        ],
        "prep_time": "15 minutes",
        "cook_time": "10 minutes",
        "total_time": "25 minutes",
        "servings": "4",
        "image_url": "http://localhost:5050/images/recipe_19.jpg"
    },
    {
        "id": "20",
        "name": "Baked Garlic Butter Shrimp",
        "description": "Juicy shrimp baked in a garlic butter sauce.",
        "ingredients": ["Shrimp", "Butter", "Garlic", "Lemon", "Parsley"],
        "main_ingredient": "shrimp",
        "steps": [
            "Preheat the oven to 375°F (190°C).",
            "In a baking dish, melt butter and mix in minced garlic, lemon juice, and chopped parsley.",
            "Add shrimp to the baking dish and toss to coat them in the garlic butter sauce.",
            "Bake in the preheated oven for about 10-12 minutes, or until the shrimp are pink and cooked through.",
            "Serve hot, garnished with fresh parsley and lemon wedges if desired."
        ],
        "prep_time": "10 minutes",
        "cook_time": "12 minutes",
        "total_time": "22 minutes",
        "servings": "4",
        "image_url": "http://localhost:5050/images/recipe_20.jpg"
    },

    {
        "id": "21",
        "name": "Delicious Chocolate Cake",
        "description": "A rich and moist chocolate cake that will satisfy your cravings.",
        "ingredients": [
            "Chicken",
            " all-purpose flour",
            "granulated sugar",
            "cup unsweetened cocoa powder",
            "teaspoons baking powder",
            "teaspoons baking soda",
            "teaspoon salt",
            "eggs",
            "milk",
            "vegetable oil",
            "vanilla extract",
            "boiling water"
        ],
        "steps": [
            "Preheat the oven to 350°F (175°C). Grease and flour two 9-inch round cake pans.",
            "In a large bowl, mix together flour, sugar, cocoa, baking powder, baking soda, and salt.",
            "Add eggs, milk, oil, and vanilla, and mix until smooth.",
            "Stir in the boiling water. The batter will be thin.",
            "Pour the batter evenly into the prepared pans.",
            "Bake for 30 to 35 minutes or until a toothpick inserted into the center comes out clean.",
            "Remove from the oven and let the cakes cool in the pans for 10 minutes.",
            "Transfer the cakes to a wire rack and let them cool completely.",
            "Frost with your favorite chocolate frosting and enjoy!"
        ],
        "prep_time": "20 minutes",
        "cook_time": "30 minutes",
        "total_time": "1 hour",
        "servings": 12,
        "image_url": "http://localhost:5050/images/recipe_21.jpg"
    },
    {
        "id": "21",
        "name": "Classic Spaghetti Carbonara",
        "description": "A traditional Italian pasta dish with a creamy sauce made from eggs, cheese, and bacon.",
        "ingredients": [
            "Fish",
            "12 ounces spaghetti",
            "2 large eggs",
            "1 cup grated Pecorino Romano cheese",
            "4 ounces pancetta or guanciale, diced",
            "2 cloves garlic, minced",
            "freshly ground black pepper",
            "Salt",
            "chopped fresh parsley"
        ],
        "steps": [
            "Bring a large pot of salted water to a boil. Cook spaghetti until al dente.",
            "In a bowl, whisk together eggs, grated Pecorino Romano cheese, black pepper, and a pinch of salt.",
            "In a skillet, cook diced pancetta or guanciale until crispy. Add minced garlic and cook for 1 minute.",
            "Drain cooked spaghetti and add it to the skillet with pancetta. Toss to coat.",
            "Remove from heat and quickly add the egg and cheese mixture. Toss until the sauce thickens and coats the pasta.",
            "Serve immediately, garnished with chopped parsley."
        ],
        "prep_time": "10 minutes",
        "cook_time": "15 minutes",
        "total_time": "25 minutes",
        "servings": 4,
        "image_url": "http://localhost:5050/images/recipe_22.jpg"
    },
    {
        "id": "22",
        "name": "Fish Parmesan",
        "description": "Breaded and fried chicken cutlets topped with marinara sauce and melted mozzarella cheese.",
        "ingredients": [
            "Fish",
            "4 boneless, skinless chicken breasts",
            "1 cup all-purpose flour",
            "2 large eggs, beaten",
            "1 1/2 cups breadcrumbs",
            "1/2 cup grated Parmesan cheese",
            "1 teaspoon dried oregano",
            "1 teaspoon dried basil",
            "1/2 teaspoon garlic powder",
            "Salt and pepper to taste",
            "1 cup marinara sauce",
            "1 1/2 cups shredded mozzarella cheese",
            "2 tablespoons chopped fresh parsley",
            "Cooking oil for frying"
        ],
        "steps": [
            "Preheat the oven to 375°F (190°C).",
            "Pound the chicken breasts to an even thickness.",
            "In separate shallow dishes, place the flour, beaten eggs, and a mixture of breadcrumbs, Parmesan cheese, dried oregano, dried basil, garlic powder, salt, and pepper.",
            "Dredge each chicken breast in flour, then dip into the beaten eggs, and finally coat with the breadcrumb mixture.",
            "In a large skillet, heat cooking oil over medium heat. Fry the breaded chicken until golden and cooked through.",
            "Place the fried chicken in a baking dish. Top with marinara sauce and shredded mozzarella cheese.",
            "Bake in the preheated oven until the cheese is melted and bubbly.",
            "Garnish with chopped fresh parsley before serving."
        ],
        "prep_time": "20 minutes",
        "cook_time": "20 minutes",
        "total_time": "40 minutes",
        "servings": 4,
        "image_url": "http://localhost:5050/images/recipe_23.jpg"
    },
    {
        "id": "23",
        "name": "Vegetable Stir-Fry",
        "description": "A colorful and healthy mix of fresh vegetables stir-fried in a flavorful sauce.",
        "ingredients": [
            "Vegi",
            "2 cups broccoli florets",
            "1 red bell pepper, sliced",
            "1 yellow bell pepper, sliced",
            "1 carrot, sliced",
            "1 cup snap peas",
            "1 cup sliced mushrooms",
            "1 tablespoon vegetable oil",
            "2 cloves garlic, minced",
            "1/4 cup soy sauce",
            "2 tablespoons oyster sauce",
            "1 tablespoon hoisin sauce",
            "1 teaspoon sesame oil",
            "1 teaspoon cornstarch",
            "1/4 cup water",
            "Sesame seeds and green onions for garnish"
        ],
        "steps": [
            "In a small bowl, mix together soy sauce, oyster sauce, hoisin sauce, sesame oil, cornstarch, and water to make the sauce.",
            "Heat vegetable oil in a wok or large skillet over high heat.",
            "Add minced garlic and stir-fry for a few seconds until fragrant.",
            "Add broccoli florets and sliced carrot. Stir-fry for 2-3 minutes until slightly tender.",
            "Add red and yellow bell peppers, snap peas, and sliced mushrooms. Stir-fry for another 2-3 minutes.",
            "Pour the sauce over the vegetables and stir to coat evenly. Cook for an additional 1-2 minutes until the sauce thickens.",
            "Remove from heat and garnish with sesame seeds and chopped green onions.",
            "Serve the vegetable stir-fry over steamed rice or noodles."
        ],
        "prep_time": "15 minutes",
        "cook_time": "10 minutes",
        "total_time": "25 minutes",
        "servings": 4,
        "image_url": "http://localhost:5050/images/recipe_24.jpg"
    },
    {
        "id": "24",
        "name": "Creamy Tomato Basil Soup",
        "description": "A comforting and creamy tomato soup with the flavors of fresh basil.",
        "ingredients": [
            "Fish",
            "2 tablespoons unsalted butter",
            "1 onion, chopped",
            "2 cloves garlic, minced",
            "28 ounces canned whole tomatoes",
            "1 cup chicken or vegetable broth",
            "1/2 cup heavy cream",
            "1/4 cup chopped fresh basil",
            "Salt and pepper to taste",
            "Croutons and additional basil for garnish"
        ],
        "steps": [
            "In a large pot, melt butter over medium heat. Add chopped onion and cook until softened.",
            "Add minced garlic and cook for another minute.",
            "Add canned whole tomatoes (with their juice) and chicken or vegetable broth. Bring to a boil, then reduce heat and simmer for about 15 minutes.",
            "Use an immersion blender to puree the soup until smooth. Alternatively, let the soup cool slightly and blend in batches using a regular blender.",
            "Return the pureed soup to the pot and stir in heavy cream and chopped fresh basil.",
            "Season with salt and pepper to taste.",
            "Serve the creamy tomato basil soup hot, garnished with croutons and additional basil leaves."
        ],
        "prep_time": "10 minutes",
        "cook_time": "20 minutes",
        "total_time": "30 minutes",
        "servings": 4,
        "image_url": "http://localhost:5050/images/recipe_25.jpg"
    },
    {
        "id": "25",
        "name": "Grilled Lemon Herb Chicken",
        "description": "Juicy and flavorful chicken marinated in a lemon herb mixture and grilled to perfection.",
        "ingredients": [
            "Pork",
            "4 boneless, skinless chicken breasts",
            "1/4 cup olive oil",
            "1/4 cup freshly squeezed lemon juice",
            "2 tablespoons chopped fresh parsley",
            "2 tablespoons chopped fresh thyme",
            "2 cloves garlic, minced",
            "1 teaspoon lemon zest",
            "Salt and pepper to taste"
        ],
        "steps": [
            "In a bowl, whisk together olive oil, lemon juice, chopped parsley, chopped thyme, minced garlic, and lemon zest.",
            "Place the chicken breasts in a resealable plastic bag or shallow dish. Pour the marinade over the chicken and ensure it's well-coated.",
            "Seal the bag or cover the dish and refrigerate for at least 1 hour, or preferably overnight.",
            "Preheat the grill to medium-high heat.",
            "Remove the chicken from the marinade and discard the marinade.",
            "Season the chicken breasts with salt and pepper.",
            "Grill the chicken for 6-7 minutes per side or until cooked through and no longer pink in the center.",
            "Remove from the grill and let the chicken rest for a few minutes before serving."
        ],
        "prep_time": "15 minutes",
        "cook_time": "15 minutes",
        "total_time": "1 hour 30 minutes",
        "servings": 4,
        "image_url": "https://example.com/lemon_herb_chicken.jpg"
    },
    {
        "id": "26",
        "name": "Shrimp Scampi",
        "description": "Tender shrimp cooked in a garlicky butter sauce served over linguine.",
        "ingredients": [
            "Shrimp",
            "8 ounces linguine",
            "1 pound large shrimp, peeled and deveined",
            "4 tablespoons unsalted butter",
            "4 cloves garlic, minced",
            "1/4 teaspoon red pepper flakes",
            "1/4 cup dry white wine",
            "2 tablespoons freshly squeezed lemon juice",
            "1/4 cup chopped fresh parsley",
            "Salt and pepper to taste",
            "Grated Parmesan cheese for serving"
        ],
        "steps": [
            "Cook linguine according to package instructions until al dente. Drain and set aside.",
            "In a large skillet, melt butter over medium heat. Add minced garlic and red pepper flakes. Cook for 1-2 minutes until fragrant.",
            "Add the shrimp to the skillet and cook for about 2-3 minutes per side until pink and cooked through.",
            "Pour in the white wine and lemon juice. Cook for another minute or until the sauce slightly reduces.",
            "Stir in chopped parsley and season with salt and pepper.",
            "Toss the cooked linguine in the shrimp scampi sauce until well coated.",
            "Serve the shrimp scampi over linguine with grated Parmesan cheese on top."
        ],
        "prep_time": "10 minutes",
        "cook_time": "15 minutes",
        "total_time": "25 minutes",
        "servings": 4,
        "image_url": "https://example.com/shrimp_scampi.jpg"
    },
    {
        "id": "27",
        "name": "Caprese Salad",
        "description": "A refreshing salad made with ripe tomatoes, fresh mozzarella, basil, and balsamic glaze.",
        "ingredients": [
            "Vegi",
            "4 ripe tomatoes, sliced",
            "8 ounces fresh mozzarella, sliced",
            "1/4 cup fresh basil leaves",
            "2 tablespoons balsamic glaze",
            "2 tablespoons extra-virgin olive oil",
            "Salt and pepper to taste"
        ],
        "steps": [
            "Arrange the sliced tomatoes and fresh mozzarella on a serving platter, alternating them.",
            "Tuck fresh basil leaves between the tomato and mozzarella slices.",
            "Drizzle balsamic glaze and extra-virgin olive oil over the salad.",
            "Season with salt and pepper to taste.",
            "Serve the Caprese salad immediately as a refreshing appetizer or side dish."
        ],
        "prep_time": "10 minutes",
        "cook_time": "0 minutes",
        "total_time": "10 minutes",
        "servings": 4,
        "image_url": "https://example.com/caprese_salad.jpg"
    },
    {
        "id": "28",
        "name": "Beef Stir-Fry with Broccoli",
        "description": "Tender beef slices and broccoli stir-fried in a savory sauce.",
        "ingredients": [
            "Beef",
            "1 pound flank steak, thinly sliced",
            "3 cups broccoli florets",
            "2 tablespoons vegetable oil",
            "3 cloves garlic, minced",
            "1/4 cup soy sauce",
            "2 tablespoons oyster sauce",
            "1 tablespoon hoisin sauce",
            "1 tablespoon cornstarch",
            "1/4 cup water",
            "1 tablespoon sesame oil",
            "2 tablespoons sesame seeds for garnish",
            "Cooked rice for serving"
        ],
        "steps": [
            "In a bowl, mix together soy sauce, oyster sauce, hoisin sauce, cornstarch, water, and sesame oil to make the sauce.",
            "Heat vegetable oil in a wok or large skillet over high heat.",
            "Add minced garlic and stir-fry for a few seconds until fragrant.",
            "Add thinly sliced beef to the skillet and stir-fry until browned and cooked through.",
            "Add broccoli florets and stir-fry for 2-3 minutes until tender-crisp.",
            "Pour the sauce over the beef and broccoli. Stir to coat evenly and cook for another minute until the sauce thickens.",
            "Remove from heat and garnish with sesame seeds.",
            "Serve the beef stir-fry with broccoli over cooked rice."
        ],
        "prep_time": "20 minutes",
        "cook_time": "10 minutes",
        "total_time": "30 minutes",
        "servings": 4,
        "image_url": "https://example.com/beef_stir_fry_broccoli.jpg"
    },
    {
        "id": "29",
        "name": "Mushroom Risotto",
        "description": "Creamy and comforting risotto with earthy mushrooms and Parmesan cheese.",
        "ingredients": [
            "1 cup Arborio rice",
            "4 cups vegetable or chicken broth",
            "1 cup sliced mushrooms",
            "1/2 cup dry white wine",
            "1/4 cup grated Parmesan cheese",
            "2 tablespoons unsalted butter",
            "1 small onion, chopped",
            "2 cloves garlic, minced",
            "2 tablespoons olive oil",
            "Salt and pepper to taste",
            "Chopped fresh parsley for garnish"
        ],
        "steps": [
            "In a saucepan, heat vegetable or chicken broth and keep it warm over low heat.",
            "In a large skillet or saucepan, heat olive oil over medium heat. Add chopped onion and cook until softened.",
            "Add minced garlic and sliced mushrooms. Cook until the mushrooms are browned and tender.",
            "Add Arborio rice to the skillet and stir to coat the rice with oil.",
            "Pour in the dry white wine and cook until it's absorbed by the rice.",
            "Gradually add warm broth to the rice, one ladleful at a time, stirring constantly and allowing the liquid to be absorbed before adding more.",
            "Continue adding broth and stirring until the rice is creamy and cooked al dente. This process takes about 20-25 minutes.",
            "Stir in grated Parmesan cheese and unsalted butter. Season with salt and pepper to taste.",
            "Garnish the mushroom risotto with chopped fresh parsley before serving."
        ],
        "prep_time": "10 minutes",
        "cook_time": "30 minutes",
        "total_time": "40 minutes",
        "servings": 4,
        "image_url": "https://example.com/mushroom_risotto.jpg"
    },
    {
        "id": "30",
        "name": "BBQ Pulled Pork Sandwiches",
        "description": "Tender pulled pork smothered in barbecue sauce and served in a soft bun.",
        "ingredients": [
            "Pork",
            "Shrimp",
            "3 pounds pork shoulder or pork butt",
            "1 cup BBQ sauce",
            "1/4 cup apple cider vinegar",
            "1/4 cup brown sugar",
            "2 teaspoons smoked paprika",
            "1 teaspoon garlic powder",
            "1 teaspoon onion powder",
            "1/2 teaspoon cayenne pepper",
            "Salt and pepper to taste",
            "8 hamburger buns",
            "Coleslaw for topping"
        ],
        "steps": [
            "In a bowl, mix together BBQ sauce, apple cider vinegar, brown sugar, smoked paprika, garlic powder, onion powder, cayenne pepper, salt, and pepper to make the marinade.",
            "Place the pork shoulder or pork butt in a slow cooker or Instant Pot. Pour the marinade over the pork.",
            "Cook the pork on low heat for 8 hours in a slow cooker or follow the Instant Pot instructions for cooking pork.",
            "Once the pork is cooked and tender, use two forks to shred the meat.",
            "Toss the shredded pork in the cooking liquid to coat it with the barbecue sauce.",
            "Serve the BBQ pulled pork on hamburger buns with coleslaw on top."
        ],
        "prep_time": "15 minutes",
        "cook_time": "8 hours (slow cooker) / 1 hour (Instant Pot)",
        "total_time": "8 hours 15 minutes (slow cooker) / 1 hour 15 minutes (Instant Pot)",
        "servings": 8,
        "image_url": "https://example.com/bbq_pulled_pork_sandwich.jpg"
    },
    {
        "id": "31",
        "name": "Pesto Pasta with Sun-Dried Tomatoes",
        "description": "Pasta tossed in a flavorful pesto sauce with sun-dried tomatoes and Parmesan cheese.",
        "ingredients": [
            "Fish",
            "Shrimp",
            "8 ounces penne or any pasta of your choice",
            "1/2 cup basil pesto",
            "1/4 cup sun-dried tomatoes, chopped",
            "1/4 cup grated Parmesan cheese",
            "2 tablespoons pine nuts, toasted",
            "2 tablespoons extra-virgin olive oil",
            "Salt and pepper to taste",
            "Fresh basil leaves for garnish"
        ],
        "steps": [
            "Cook pasta according to package instructions until al dente. Drain and set aside.",
            "In a large mixing bowl, toss the cooked pasta with basil pesto until well coated.",
            "Add chopped sun-dried tomatoes, grated Parmesan cheese, and toasted pine nuts to the pasta. Mix well.",
            "Drizzle extra-virgin olive oil over the pasta and season with salt and pepper to taste.",
            "Garnish the pesto pasta with fresh basil leaves before serving."
        ],
        "prep_time": "10 minutes",
        "cook_time": "10 minutes",
        "total_time": "20 minutes",
        "servings": 4,
        "image_url": "https://example.com/pesto_pasta_sun_dried_tomatoes.jpg"
    },
    {
        "id": "32",
        "name": "Lemon Raspberry Cheesecake",
        "description": "A luscious cheesecake with a lemon-flavored filling and a raspberry swirl.",
        "ingredients": [
            "Vegi",
            "1 1/2 cups graham cracker crumbs",
            "1/4 cup granulated sugar",
            "1/2 cup unsalted butter, melted",
            "16 ounces cream cheese, softened",
            "1 cup granulated sugar",
            "3 large eggs",
            "1/2 cup sour cream",
            "1/4 cup fresh lemon juice",
            "1 tablespoon lemon zest",
            "1 teaspoon vanilla extract",
            "1/2 cup raspberry jam or puree",
            "Fresh raspberries for garnish"
        ],
        "steps": [
            "Preheat the oven to 325°F (160°C).",
            "In a bowl, mix graham cracker crumbs, granulated sugar, and melted butter until the crumbs are evenly moistened.",
            "Press the crumb mixture into the bottom of a 9-inch springform pan to create the crust.",
            "In a large mixing bowl, beat cream cheese and granulated sugar until smooth and creamy.",
            "Add eggs one at a time, beating well after each addition.",
            "Mix in sour cream, fresh lemon juice, lemon zest, and vanilla extract.",
            "Pour the cream cheese mixture over the crust in the springform pan.",
            "Drop spoonfuls of raspberry jam or puree on top of the cheesecake filling.",
            "Use a toothpick or knife to create a swirl pattern with the raspberry jam.",
            "Bake the cheesecake in the preheated oven for about 50-60 minutes or until the center is set.",
            "Remove from the oven and let the cheesecake cool in the pan for about an hour.",
            "Refrigerate the cheesecake for at least 4 hours or overnight before serving.",
            "Garnish with fresh raspberries before serving."
        ],
        "prep_time": "20 minutes",
        "cook_time": "1 hour",
        "total_time": "5 hours",
        "servings": 12,
        "image_url": "https://example.com/lemon_raspberry_cheesecake.jpg"
    },
    {
        "id": "33",
        "name": "Homemade Margherita Pizza",
        "description": "A classic Margherita pizza with a thin crust, tomato sauce, fresh mozzarella, and basil.",
        "ingredients": [
            "Chicken",
            "Pork",
            "1 pound pizza dough",
            "1/2 cup pizza sauce or marinara sauce",
            "8 ounces fresh mozzarella, sliced",
            "1/4 cup fresh basil leaves",
            "2 tablespoons extra-virgin olive oil",
            "1/2 teaspoon dried oregano",
            "Salt and pepper to taste",
            "Cornmeal or flour for dusting"
        ],
        "steps": [
            "Preheat the oven to the highest temperature your oven can reach (usually 500°F or 260°C).",
            "On a floured surface, roll out the pizza dough into a 12-inch circle.",
            "Transfer the rolled-out dough to a baking sheet or pizza stone dusted with cornmeal or flour.",
            "Spread pizza sauce evenly over the dough, leaving a small border around the edges.",
            "Arrange sliced mozzarella on top of the sauce.",
            "Season with dried oregano, salt, and pepper.",
            "Bake the pizza in the preheated oven for about 10-15 minutes or until the crust is golden and the cheese is bubbly and slightly browned.",
            "Remove the pizza from the oven and top with fresh basil leaves.",
            "Drizzle extra-virgin olive oil over the pizza before serving."
        ],
        "prep_time": "15 minutes",
        "cook_time": "15 minutes",
        "total_time": "30 minutes",
        "servings": 4,
        "image_url": "https://example.com/margherita_pizza.jpg"
    }
]
